wialonpy/__init__.py
wialonpy/utils.py
wialonpy-0.1.11.dist-info/licenses/LICENSE
wialonpy-0.1.11.dist-info/METADATA
wialonpy-0.1.11.dist-info/WHEEL
wialonpy-0.1.11.dist-info/top_level.txt
wialonpy-0.1.11.dist-info/RECORD
