Metadata-Version: 2.4
Name: wialonpy
Version: 0.1.11
Summary: A lightweight Python wrapper for the Wialon API by Gurtam
Home-page: https://github.com/slv177/wialonpy
Author: Viacheslav Shambazov
Author-email: Viacheslav Shambazov <shambazov@gmail.com>
License: MIT
Project-URL: Homepage, https://github.com/slv177/wialonpy
Project-URL: Repository, https://github.com/slv177/wialonpy
Requires-Python: >=3.10
License-File: LICENSE
Requires-Dist: requests
Requires-Dist: pytest
Dynamic: author
Dynamic: home-page
Dynamic: license-file
Dynamic: requires-python
